cgls_cpe/__init__.py
cgls_cpe/db_api.py
cgls_cpe/cfg/.Rhistory
cgls_cpe/cfg/.gitignore
cgls_cpe/cfg/Readme.txt
cgls_cpe/cfg/logging-conf.json
cgls_cpe/cfg/s3-permissions.json
cgls_cpe/cfg/settings.toml
cgls_cpe/cfg/deploy-specific/settings-prod.toml
cgls_cpe/cfg/deploy-specific/settings-staging.toml
cgls_cpe/cfg/deploy-specific/settings-ut.toml
cgls_cpe/common/__init__.py
cgls_cpe/common/cgl_pv_grid_333m-geo.json
cgls_cpe/common/cgl_s3_grid-geo.json
cgls_cpe/common/cloud_helper.py
cgls_cpe/common/grid.py
cgls_cpe/common/helper.py
cgls_cpe/common/launcher_sandbox.py
cgls_cpe/common/launcher_with_mounts.py
cgls_cpe/common/products.py
cgls_cpe/config/__init__.py
cgls_cpe/config/configuration.py
cgls_cpe/config/database.py
cgls_cpe/config/input.py
cgls_cpe/config/processing.py
cgls_cpe/config/secrets.py
cgls_cpe/config/storage.py
cgls_cpe/config/model/__init__.py
cgls_cpe/config/model/ancillary_data.py
cgls_cpe/config/model/area.py
cgls_cpe/config/model/context.py
cgls_cpe/config/model/data_object.py
cgls_cpe/config/model/enums.py
cgls_cpe/config/model/sat_image.py
cgls_cpe/config/model/subtypes.py
cgls_cpe/config/model/timestamp.py
cgls_cpe/config/model/version.py
cgls_cpe/cpl/__init__.py
cgls_cpe/cpl/date_time.py
cgls_cpe/cpl/geotiff.py
cgls_cpe/cpl/grid.py
cgls_cpe/cpl/netcdf.py
cgls_cpe/cpl/product.py
cgls_cpe/cpl/transfer.py
cgls_cpe/exceptions/__init__.py
cgls_cpe/exceptions/exception.py
cgls_cpe/hspf/__init__.py
cgls_cpe/hspf/common_helpers.py
cgls_cpe/logging/__init__.py
cgls_cpe/logging/log.py
cgls_cpe/processing/__init__.py
cgls_cpe/processing/manager.py
cgls_cpe/processing/processing_status_handler.py
cgls_cpe/processing/updaters.py
cgls_cpe/storage/PRIP_store.py
cgls_cpe/storage/__init__.py
cgls_cpe/storage/eodata_store.py
cgls_cpe/storage/local_storage.py
cgls_cpe/storage/remote_storage.py
cgls_cpe/storage/implementation/__init__.py
cgls_cpe/storage/implementation/s3_api.py
cgls_cpe/testing/__init__.py
cgls_cpe/testing/test_data.py
cgls_cpe-0.0.41.dist-info/METADATA
cgls_cpe-0.0.41.dist-info/WHEEL
cgls_cpe-0.0.41.dist-info/licenses/LICENSE
cgls_cpe-0.0.41.dist-info/RECORD
